docin-0.1.2.dist-info/licenses/LICENSE.txt
ocr/__init__.py
ocr/mist_ocr.py
ocr/query/__init__.py
ocr/query/query_engine.py
ocr/query/renderer.py
docin-0.1.2.dist-info/METADATA
docin-0.1.2.dist-info/WHEEL
docin-0.1.2.dist-info/top_level.txt
docin-0.1.2.dist-info/RECORD
