Metadata-Version: 2.4
Name: docin
Version: 0.1.2
Summary: A Python package for performing OCR and document indexing on legacy documents using the Mistral Ocr API.
Author: ['Ime Inyang']
Author-email: alfiinyang@gmail.com
License-File: LICENSE.txt
Requires-Dist: mistralai
Requires-Dist: datauri
Requires-Dist: langchain-core
Requires-Dist: spacy
Requires-Dist: IPython
Dynamic: author
Dynamic: author-email
Dynamic: description
Dynamic: description-content-type
Dynamic: license-file
Dynamic: requires-dist
Dynamic: summary
